xhs_bailian_mcp_server_cds007/__init__.py
xhs_bailian_mcp_server_cds007/server.py
xhs_bailian_mcp_server_cds007-0.1.6.dist-info/METADATA
xhs_bailian_mcp_server_cds007-0.1.6.dist-info/WHEEL
xhs_bailian_mcp_server_cds007-0.1.6.dist-info/entry_points.txt
xhs_bailian_mcp_server_cds007-0.1.6.dist-info/RECORD
